mcssmapi/__init__.py
mcssmapi/mcssmapi.py
mCSSMapi-0.1.dist-info/LICENSE
mCSSMapi-0.1.dist-info/METADATA
mCSSMapi-0.1.dist-info/WHEEL
mCSSMapi-0.1.dist-info/top_level.txt
mCSSMapi-0.1.dist-info/RECORD
