Metadata-Version: 2.1
Name: mCSSMapi
Version: 0.1
Summary: The mcssmapi library providing access to Cisco Smart Account licensing API with python.
Home-page: https://github.com/mmikulic212/mcssmapi
Author: Michael Mikulic
Author-email: 
License: UNKNOWN
Project-URL: Bug Tracker, https://github.com/mmikulic212/mcssmapi/issues
Platform: UNKNOWN
Classifier: Programming Language :: Python :: 3
Classifier: License :: OSI Approved :: MIT License
Classifier: Operating System :: OS Independent
Requires-Python: >=3.6
License-File: LICENSE
